did_stuff/__init__.py
did_stuff/cli.py
did_stuff/commit_message_generator.py
did_stuff/config.py
did_stuff/git_hooks.py
did_stuff/tui.py
did_stuff-0.1.6.dist-info/METADATA
did_stuff-0.1.6.dist-info/WHEEL
did_stuff-0.1.6.dist-info/entry_points.txt
did_stuff-0.1.6.dist-info/top_level.txt
did_stuff-0.1.6.dist-info/RECORD
