Metadata-Version: 2.2
Name: did-stuff
Version: 0.1.6
Summary: AI-powered Git commit message generator
Author-email: Jarad DeLorenzo <jaradd@gmail.com>
License: MIT
Keywords: git,commit,message,generator,AI
Classifier: Programming Language :: Python :: 3
Classifier: License :: OSI Approved :: MIT License
Classifier: Operating System :: OS Independent
Requires-Dist: click>=8.1.3
Requires-Dist: openai>=0.27.0
Requires-Dist: boto3>=1.26
Provides-Extra: dev
Requires-Dist: pytest>=7.4.3; extra == "dev"
Requires-Dist: pytest-cov>=4.0.0; extra == "dev"
